{
  "image": {
    "width": 499,
    "height": 333,
    "filename": "00002422.jpg",
    "original_filename": "2242694036_da407e8522.jpg",
    "url": "https://darwin.v7labs.com/api/images/3600/original?token=41995adc-89c1-4dd8-8552-3c76ba5e1f0a",
    "thumbnail_url": "https://darwin.v7labs.com/api/images/3600/thumbnail?token=41995adc-89c1-4dd8-8552-3c76ba5e1f0a",
    "workview_url": "https://darwin.v7labs.com/workview?dataset=17&image=2422"
  },
  "dataset": "Bird Species",
  "annotated": true,
  "annotations": [
    {
      "name": "European Robin",
      "polygon": {
        "path": [
          {
            "x": 114.73,
            "y": 232.46
          },
          {
            "x": 134.23,
            "y": 223.86
          },
          {
            "x": 147.42,
            "y": 217.56
          },
          {
            "x": 154.87,
            "y": 216.98
          },
          {
            "x": 161.18,
            "y": 215.26
          },
          {
            "x": 167.49,
            "y": 215.26
          },
          {
            "x": 172.07,
            "y": 215.26
          },
          {
            "x": 167.49,
            "y": 221.57
          },
          {
            "x": 154.87,
            "y": 230.74
          },
          {
            "x": 154.3,
            "y": 231.89
          },
          {
            "x": 165.19,
            "y": 233.04
          },
          {
            "x": 182.97,
            "y": 225.58
          },
          {
            "x": 189.28,
            "y": 225.58
          },
          {
            "x": 193.29,
            "y": 234.76
          },
          {
            "x": 200.17,
            "y": 239.35
          },
          {
            "x": 212.79,
            "y": 241.07
          },
          {
            "x": 217.95,
            "y": 239.92
          },
          {
            "x": 227.12,
            "y": 250.24
          },
          {
            "x": 235.72,
            "y": 257.12
          },
          {
            "x": 239.16,
            "y": 261.71
          },
          {
            "x": 250.06,
            "y": 258.27
          },
          {
            "x": 246.04,
            "y": 251.96
          },
          {
            "x": 236.87,
            "y": 249.09
          },
          {
            "x": 228.84,
            "y": 243.36
          },
          {
            "x": 234.0,
            "y": 237.62
          },
          {
            "x": 245.47,
            "y": 229.02
          },
          {
            "x": 266.69,
            "y": 217.56
          },
          {
            "x": 279.87,
            "y": 205.51
          },
          {
            "x": 285.04,
            "y": 199.78
          },
          {
            "x": 290.77,
            "y": 179.71
          },
          {
            "x": 285.61,
            "y": 174.55
          },
          {
            "x": 283.32,
            "y": 161.36
          },
          {
            "x": 283.32,
            "y": 155.63
          },
          {
            "x": 289.05,
            "y": 152.19
          },
          {
            "x": 289.05,
            "y": 148.17
          },
          {
            "x": 279.87,
            "y": 148.17
          },
          {
            "x": 278.15,
            "y": 138.43
          },
          {
            "x": 264.97,
            "y": 132.69
          },
          {
            "x": 250.63,
            "y": 135.56
          },
          {
            "x": 237.44,
            "y": 141.29
          },
          {
            "x": 231.14,
            "y": 151.04
          },
          {
            "x": 210.49,
            "y": 161.94
          },
          {
            "x": 196.16,
            "y": 168.24
          },
          {
            "x": 190.42,
            "y": 177.99
          },
          {
            "x": 177.81,
            "y": 186.02
          },
          {
            "x": 163.47,
            "y": 196.34
          },
          {
            "x": 147.42,
            "y": 207.23
          },
          {
            "x": 117.6,
            "y": 222.72
          },
          {
            "x": 110.72,
            "y": 228.45
          },
          {
            "x": 106.71,
            "y": 233.61
          }
        ]
      }
    },
    {
      "name": "European Robin tag",
      "tag": {}
    }
  ]
}