{
  "image": {
    "width": 499,
    "height": 333,
    "filename": "00002802.jpg",
    "original_filename": "2720464450_87796393b7.jpg",
    "url": "https://darwin.v7labs.com/api/images/3980/original?token=41995adc-89c1-4dd8-8552-3c76ba5e1f0a",
    "thumbnail_url": "https://darwin.v7labs.com/api/images/3980/thumbnail?token=41995adc-89c1-4dd8-8552-3c76ba5e1f0a",
    "workview_url": "https://darwin.v7labs.com/workview?dataset=17&image=2802"
  },
  "dataset": "Bird Species",
  "annotated": true,
  "annotations": [
    {
      "name": "European Robin",
      "polygon": {
        "path": [
          {
            "x": 181.1,
            "y": 121.01
          },
          {
            "x": 182.27,
            "y": 111.66
          },
          {
            "x": 188.4,
            "y": 99.97
          },
          {
            "x": 195.71,
            "y": 91.49
          },
          {
            "x": 209.16,
            "y": 88.28
          },
          {
            "x": 223.48,
            "y": 88.57
          },
          {
            "x": 245.69,
            "y": 95.0
          },
          {
            "x": 263.52,
            "y": 104.35
          },
          {
            "x": 278.14,
            "y": 110.49
          },
          {
            "x": 294.5,
            "y": 120.14
          },
          {
            "x": 298.3,
            "y": 127.74
          },
          {
            "x": 301.52,
            "y": 135.04
          },
          {
            "x": 305.03,
            "y": 140.89
          },
          {
            "x": 309.7,
            "y": 146.44
          },
          {
            "x": 317.3,
            "y": 150.24
          },
          {
            "x": 318.18,
            "y": 156.09
          },
          {
            "x": 323.15,
            "y": 165.73
          },
          {
            "x": 327.53,
            "y": 172.16
          },
          {
            "x": 337.18,
            "y": 188.53
          },
          {
            "x": 340.1,
            "y": 199.35
          },
          {
            "x": 340.39,
            "y": 204.9
          },
          {
            "x": 337.76,
            "y": 208.99
          },
          {
            "x": 326.66,
            "y": 209.87
          },
          {
            "x": 316.13,
            "y": 211.33
          },
          {
            "x": 311.46,
            "y": 209.58
          },
          {
            "x": 307.37,
            "y": 217.47
          },
          {
            "x": 301.81,
            "y": 225.95
          },
          {
            "x": 295.09,
            "y": 231.21
          },
          {
            "x": 292.17,
            "y": 231.21
          },
          {
            "x": 286.32,
            "y": 230.62
          },
          {
            "x": 285.15,
            "y": 249.04
          },
          {
            "x": 286.61,
            "y": 256.93
          },
          {
            "x": 288.66,
            "y": 261.61
          },
          {
            "x": 289.24,
            "y": 265.7
          },
          {
            "x": 287.49,
            "y": 266.28
          },
          {
            "x": 280.77,
            "y": 259.56
          },
          {
            "x": 277.55,
            "y": 266.57
          },
          {
            "x": 275.8,
            "y": 270.96
          },
          {
            "x": 271.71,
            "y": 271.25
          },
          {
            "x": 271.41,
            "y": 268.91
          },
          {
            "x": 275.21,
            "y": 260.44
          },
          {
            "x": 268.2,
            "y": 268.04
          },
          {
            "x": 262.94,
            "y": 272.42
          },
          {
            "x": 263.23,
            "y": 267.45
          },
          {
            "x": 269.37,
            "y": 261.61
          },
          {
            "x": 271.41,
            "y": 258.1
          },
          {
            "x": 277.55,
            "y": 254.01
          },
          {
            "x": 279.89,
            "y": 249.33
          },
          {
            "x": 282.81,
            "y": 230.33
          },
          {
            "x": 275.8,
            "y": 235.3
          },
          {
            "x": 267.61,
            "y": 242.31
          },
          {
            "x": 257.38,
            "y": 245.82
          },
          {
            "x": 247.74,
            "y": 244.36
          },
          {
            "x": 245.4,
            "y": 243.19
          },
          {
            "x": 234.88,
            "y": 261.9
          },
          {
            "x": 235.46,
            "y": 267.74
          },
          {
            "x": 238.68,
            "y": 273.59
          },
          {
            "x": 242.19,
            "y": 280.6
          },
          {
            "x": 242.19,
            "y": 285.28
          },
          {
            "x": 235.17,
            "y": 280.31
          },
          {
            "x": 231.37,
            "y": 273.3
          },
          {
            "x": 229.62,
            "y": 272.42
          },
          {
            "x": 231.66,
            "y": 282.94
          },
          {
            "x": 234.29,
            "y": 287.91
          },
          {
            "x": 237.8,
            "y": 290.83
          },
          {
            "x": 243.35,
            "y": 293.47
          },
          {
            "x": 244.82,
            "y": 294.63
          },
          {
            "x": 243.65,
            "y": 297.85
          },
          {
            "x": 236.34,
            "y": 295.8
          },
          {
            "x": 231.66,
            "y": 293.47
          },
          {
            "x": 226.11,
            "y": 293.17
          },
          {
            "x": 222.31,
            "y": 284.99
          },
          {
            "x": 222.31,
            "y": 274.76
          },
          {
            "x": 223.77,
            "y": 267.45
          },
          {
            "x": 230.49,
            "y": 258.1
          },
          {
            "x": 238.39,
            "y": 244.65
          },
          {
            "x": 227.28,
            "y": 241.15
          },
          {
            "x": 217.34,
            "y": 239.39
          },
          {
            "x": 205.65,
            "y": 231.21
          },
          {
            "x": 194.25,
            "y": 220.68
          },
          {
            "x": 186.94,
            "y": 210.45
          },
          {
            "x": 181.1,
            "y": 194.38
          },
          {
            "x": 177.59,
            "y": 183.56
          },
          {
            "x": 174.37,
            "y": 173.63
          },
          {
            "x": 176.42,
            "y": 163.98
          },
          {
            "x": 179.93,
            "y": 154.92
          },
          {
            "x": 179.93,
            "y": 146.74
          },
          {
            "x": 179.93,
            "y": 139.72
          },
          {
            "x": 181.1,
            "y": 132.71
          },
          {
            "x": 168.53,
            "y": 130.08
          },
          {
            "x": 165.31,
            "y": 125.69
          },
          {
            "x": 172.33,
            "y": 122.48
          },
          {
            "x": 181.1,
            "y": 121.89
          }
        ]
      }
    },
    {
      "name": "European Robin tag",
      "tag": {}
    }
  ]
}