{
  "image": {
    "width": 333,
    "height": 500,
    "filename": "00000197.jpg",
    "original_filename": "1839053545_c9a80e02b2.jpg",
    "url": "https://darwin.v7labs.com/api/images/1370/original?token=41995adc-89c1-4dd8-8552-3c76ba5e1f0a",
    "thumbnail_url": "https://darwin.v7labs.com/api/images/1370/thumbnail?token=41995adc-89c1-4dd8-8552-3c76ba5e1f0a",
    "workview_url": "https://darwin.v7labs.com/workview?dataset=17&image=197"
  },
  "dataset": "Bird Species",
  "annotated": true,
  "annotations": [
    {
      "name": "African Grey Parrot",
      "polygon": {
        "path": [
          {
            "x": 61.06,
            "y": 44.55
          },
          {
            "x": 56.77,
            "y": 50.16
          },
          {
            "x": 56.11,
            "y": 56.44
          },
          {
            "x": 52.14,
            "y": 60.4
          },
          {
            "x": 45.87,
            "y": 65.68
          },
          {
            "x": 39.93,
            "y": 72.61
          },
          {
            "x": 34.65,
            "y": 81.19
          },
          {
            "x": 32.01,
            "y": 89.44
          },
          {
            "x": 31.02,
            "y": 99.67
          },
          {
            "x": 34.32,
            "y": 110.78
          },
          {
            "x": 40.26,
            "y": 119.69
          },
          {
            "x": 46.86,
            "y": 125.3
          },
          {
            "x": 43.89,
            "y": 117.38
          },
          {
            "x": 43.89,
            "y": 107.81
          },
          {
            "x": 50.49,
            "y": 114.41
          },
          {
            "x": 56.11,
            "y": 116.06
          },
          {
            "x": 71.29,
            "y": 117.71
          },
          {
            "x": 71.62,
            "y": 122.33
          },
          {
            "x": 76.24,
            "y": 125.3
          },
          {
            "x": 79.21,
            "y": 124.97
          },
          {
            "x": 79.21,
            "y": 131.57
          },
          {
            "x": 85.15,
            "y": 132.56
          },
          {
            "x": 86.14,
            "y": 135.86
          },
          {
            "x": 89.44,
            "y": 139.82
          },
          {
            "x": 92.41,
            "y": 142.13
          },
          {
            "x": 93.4,
            "y": 148.73
          },
          {
            "x": 87.13,
            "y": 155.99
          },
          {
            "x": 82.51,
            "y": 169.2
          },
          {
            "x": 81.52,
            "y": 173.82
          },
          {
            "x": 81.52,
            "y": 185.04
          },
          {
            "x": 81.52,
            "y": 193.62
          },
          {
            "x": 84.16,
            "y": 197.58
          },
          {
            "x": 85.15,
            "y": 207.92
          },
          {
            "x": 86.47,
            "y": 218.81
          },
          {
            "x": 89.44,
            "y": 227.39
          },
          {
            "x": 90.76,
            "y": 236.63
          },
          {
            "x": 93.73,
            "y": 247.52
          },
          {
            "x": 96.7,
            "y": 257.75
          },
          {
            "x": 101.32,
            "y": 266.0
          },
          {
            "x": 107.92,
            "y": 275.24
          },
          {
            "x": 111.55,
            "y": 280.86
          },
          {
            "x": 115.51,
            "y": 286.14
          },
          {
            "x": 118.48,
            "y": 294.39
          },
          {
            "x": 122.44,
            "y": 300.99
          },
          {
            "x": 128.38,
            "y": 312.54
          },
          {
            "x": 122.44,
            "y": 320.13
          },
          {
            "x": 121.78,
            "y": 327.72
          },
          {
            "x": 124.42,
            "y": 336.3
          },
          {
            "x": 127.39,
            "y": 345.87
          },
          {
            "x": 130.36,
            "y": 352.8
          },
          {
            "x": 136.3,
            "y": 361.38
          },
          {
            "x": 140.26,
            "y": 365.34
          },
          {
            "x": 141.91,
            "y": 367.98
          },
          {
            "x": 143.56,
            "y": 371.28
          },
          {
            "x": 149.83,
            "y": 366.99
          },
          {
            "x": 149.83,
            "y": 352.47
          },
          {
            "x": 153.79,
            "y": 352.14
          },
          {
            "x": 160.72,
            "y": 362.7
          },
          {
            "x": 170.96,
            "y": 373.48
          },
          {
            "x": 180.86,
            "y": 382.39
          },
          {
            "x": 190.43,
            "y": 390.98
          },
          {
            "x": 203.96,
            "y": 403.19
          },
          {
            "x": 201.32,
            "y": 430.25
          },
          {
            "x": 200.99,
            "y": 439.82
          },
          {
            "x": 206.27,
            "y": 449.06
          },
          {
            "x": 211.22,
            "y": 457.97
          },
          {
            "x": 220.13,
            "y": 464.24
          },
          {
            "x": 229.04,
            "y": 469.19
          },
          {
            "x": 241.58,
            "y": 468.53
          },
          {
            "x": 249.5,
            "y": 469.19
          },
          {
            "x": 260.72,
            "y": 469.85
          },
          {
            "x": 269.63,
            "y": 467.87
          },
          {
            "x": 274.91,
            "y": 455.99
          },
          {
            "x": 277.89,
            "y": 456.65
          },
          {
            "x": 280.86,
            "y": 454.34
          },
          {
            "x": 277.22,
            "y": 444.11
          },
          {
            "x": 281.19,
            "y": 445.1
          },
          {
            "x": 282.84,
            "y": 439.16
          },
          {
            "x": 278.88,
            "y": 430.58
          },
          {
            "x": 279.87,
            "y": 396.7
          },
          {
            "x": 278.22,
            "y": 383.82
          },
          {
            "x": 280.86,
            "y": 372.71
          },
          {
            "x": 280.53,
            "y": 347.3
          },
          {
            "x": 289.44,
            "y": 352.58
          },
          {
            "x": 290.43,
            "y": 331.68
          },
          {
            "x": 284.82,
            "y": 245.65
          },
          {
            "x": 276.56,
            "y": 199.01
          },
          {
            "x": 266.99,
            "y": 174.26
          },
          {
            "x": 253.13,
            "y": 149.72
          },
          {
            "x": 237.62,
            "y": 134.54
          },
          {
            "x": 219.8,
            "y": 121.34
          },
          {
            "x": 215.51,
            "y": 121.34
          },
          {
            "x": 207.59,
            "y": 114.74
          },
          {
            "x": 195.71,
            "y": 107.81
          },
          {
            "x": 197.69,
            "y": 101.21
          },
          {
            "x": 194.72,
            "y": 96.26
          },
          {
            "x": 192.74,
            "y": 90.98
          },
          {
            "x": 185.81,
            "y": 81.74
          },
          {
            "x": 180.53,
            "y": 75.8
          },
          {
            "x": 176.57,
            "y": 68.87
          },
          {
            "x": 172.94,
            "y": 61.28
          },
          {
            "x": 167.66,
            "y": 57.65
          },
          {
            "x": 156.43,
            "y": 48.4
          },
          {
            "x": 148.51,
            "y": 41.14
          },
          {
            "x": 139.27,
            "y": 36.85
          },
          {
            "x": 128.71,
            "y": 36.85
          },
          {
            "x": 121.12,
            "y": 35.86
          },
          {
            "x": 105.61,
            "y": 34.21
          },
          {
            "x": 96.04,
            "y": 33.88
          },
          {
            "x": 84.49,
            "y": 34.21
          },
          {
            "x": 74.92,
            "y": 38.17
          },
          {
            "x": 65.02,
            "y": 41.47
          }
        ]
      }
    },
    {
      "name": "African Grey",
      "tag": {}
    }
  ]
}