{
  "image": {
    "width": 400,
    "height": 500,
    "filename": "00000232.jpg",
    "original_filename": "2830695541_47094bae27.jpg",
    "url": "https://darwin.v7labs.com/api/images/1405/original?token=41995adc-89c1-4dd8-8552-3c76ba5e1f0a",
    "thumbnail_url": "https://darwin.v7labs.com/api/images/1405/thumbnail?token=41995adc-89c1-4dd8-8552-3c76ba5e1f0a",
    "workview_url": "https://darwin.v7labs.com/workview?dataset=17&image=232"
  },
  "dataset": "Bird Species",
  "annotated": true,
  "annotations": [
    {
      "name": "African Grey Parrot",
      "polygon": {
        "path": [
          {
            "x": 108.0,
            "y": 309.1
          },
          {
            "x": 113.95,
            "y": 320.0
          },
          {
            "x": 122.87,
            "y": 327.93
          },
          {
            "x": 138.72,
            "y": 360.63
          },
          {
            "x": 159.54,
            "y": 372.53
          },
          {
            "x": 188.28,
            "y": 395.32
          },
          {
            "x": 217.02,
            "y": 419.11
          },
          {
            "x": 247.74,
            "y": 443.88
          },
          {
            "x": 265.58,
            "y": 450.82
          },
          {
            "x": 260.63,
            "y": 432.98
          },
          {
            "x": 264.59,
            "y": 425.05
          },
          {
            "x": 272.52,
            "y": 419.11
          },
          {
            "x": 272.52,
            "y": 412.17
          },
          {
            "x": 290.36,
            "y": 410.19
          },
          {
            "x": 292.34,
            "y": 435.95
          },
          {
            "x": 296.31,
            "y": 449.83
          },
          {
            "x": 322.07,
            "y": 423.07
          },
          {
            "x": 341.89,
            "y": 354.69
          },
          {
            "x": 348.83,
            "y": 324.95
          },
          {
            "x": 345.86,
            "y": 297.2
          },
          {
            "x": 336.94,
            "y": 284.32
          },
          {
            "x": 346.85,
            "y": 242.03
          },
          {
            "x": 348.83,
            "y": 230.14
          },
          {
            "x": 355.77,
            "y": 218.25
          },
          {
            "x": 355.77,
            "y": 192.48
          },
          {
            "x": 353.79,
            "y": 161.76
          },
          {
            "x": 355.77,
            "y": 141.93
          },
          {
            "x": 342.89,
            "y": 122.11
          },
          {
            "x": 322.07,
            "y": 89.74
          },
          {
            "x": 309.19,
            "y": 67.93
          },
          {
            "x": 296.31,
            "y": 56.04
          },
          {
            "x": 277.47,
            "y": 50.09
          },
          {
            "x": 256.66,
            "y": 40.18
          },
          {
            "x": 236.84,
            "y": 35.23
          },
          {
            "x": 210.08,
            "y": 29.28
          },
          {
            "x": 171.43,
            "y": 40.18
          },
          {
            "x": 136.74,
            "y": 51.09
          },
          {
            "x": 112.96,
            "y": 64.96
          },
          {
            "x": 81.24,
            "y": 92.71
          },
          {
            "x": 75.29,
            "y": 119.47
          },
          {
            "x": 59.44,
            "y": 152.18
          },
          {
            "x": 62.41,
            "y": 180.92
          },
          {
            "x": 73.31,
            "y": 211.64
          },
          {
            "x": 77.28,
            "y": 245.34
          },
          {
            "x": 83.22,
            "y": 286.96
          },
          {
            "x": 87.19,
            "y": 309.76
          },
          {
            "x": 90.16,
            "y": 319.67
          }
        ]
      }
    },
    {
      "name": "African Grey",
      "tag": {}
    }
  ]
}