{
  "image": {
    "width": 500,
    "height": 375,
    "filename": "00000466.jpg",
    "original_filename": "87591035_fd5833b66a.jpg",
    "url": "https://darwin.v7labs.com/api/images/1639/original?token=41995adc-89c1-4dd8-8552-3c76ba5e1f0a",
    "thumbnail_url": "https://darwin.v7labs.com/api/images/1639/thumbnail?token=41995adc-89c1-4dd8-8552-3c76ba5e1f0a",
    "workview_url": "https://darwin.v7labs.com/workview?dataset=17&image=466"
  },
  "dataset": "Bird Species",
  "annotated": true,
  "annotations": [
    {
      "name": "African Grey Parrot",
      "polygon": {
        "path": [
          {
            "x": 230.81,
            "y": 234.41
          },
          {
            "x": 235.2,
            "y": 235.88
          },
          {
            "x": 241.04,
            "y": 236.17
          },
          {
            "x": 246.02,
            "y": 234.12
          },
          {
            "x": 251.86,
            "y": 230.03
          },
          {
            "x": 254.79,
            "y": 237.05
          },
          {
            "x": 254.5,
            "y": 249.33
          },
          {
            "x": 250.11,
            "y": 249.91
          },
          {
            "x": 246.6,
            "y": 250.79
          },
          {
            "x": 246.6,
            "y": 250.79
          },
          {
            "x": 249.82,
            "y": 255.76
          },
          {
            "x": 254.79,
            "y": 260.15
          },
          {
            "x": 258.59,
            "y": 264.83
          },
          {
            "x": 260.34,
            "y": 269.5
          },
          {
            "x": 262.98,
            "y": 268.04
          },
          {
            "x": 264.15,
            "y": 263.07
          },
          {
            "x": 267.65,
            "y": 268.63
          },
          {
            "x": 272.33,
            "y": 273.01
          },
          {
            "x": 273.21,
            "y": 269.8
          },
          {
            "x": 270.87,
            "y": 262.78
          },
          {
            "x": 268.53,
            "y": 255.76
          },
          {
            "x": 267.07,
            "y": 246.99
          },
          {
            "x": 269.12,
            "y": 226.81
          },
          {
            "x": 271.16,
            "y": 213.95
          },
          {
            "x": 274.38,
            "y": 206.93
          },
          {
            "x": 279.35,
            "y": 206.05
          },
          {
            "x": 282.86,
            "y": 203.42
          },
          {
            "x": 290.46,
            "y": 189.09
          },
          {
            "x": 290.46,
            "y": 189.09
          },
          {
            "x": 291.92,
            "y": 183.24
          },
          {
            "x": 294.26,
            "y": 175.93
          },
          {
            "x": 295.14,
            "y": 170.38
          },
          {
            "x": 292.8,
            "y": 162.77
          },
          {
            "x": 292.8,
            "y": 162.77
          },
          {
            "x": 295.43,
            "y": 160.73
          },
          {
            "x": 299.23,
            "y": 156.05
          },
          {
            "x": 302.45,
            "y": 148.15
          },
          {
            "x": 304.5,
            "y": 141.13
          },
          {
            "x": 305.08,
            "y": 134.7
          },
          {
            "x": 302.74,
            "y": 131.78
          },
          {
            "x": 302.74,
            "y": 131.49
          },
          {
            "x": 301.87,
            "y": 127.1
          },
          {
            "x": 296.31,
            "y": 120.96
          },
          {
            "x": 285.2,
            "y": 119.2
          },
          {
            "x": 279.64,
            "y": 119.2
          },
          {
            "x": 269.7,
            "y": 122.42
          },
          {
            "x": 264.15,
            "y": 129.15
          },
          {
            "x": 260.64,
            "y": 137.04
          },
          {
            "x": 260.64,
            "y": 137.04
          },
          {
            "x": 256.84,
            "y": 143.18
          },
          {
            "x": 250.11,
            "y": 144.35
          },
          {
            "x": 243.38,
            "y": 146.11
          },
          {
            "x": 236.37,
            "y": 147.57
          },
          {
            "x": 229.64,
            "y": 146.98
          },
          {
            "x": 226.72,
            "y": 148.44
          },
          {
            "x": 222.04,
            "y": 152.25
          },
          {
            "x": 214.44,
            "y": 155.46
          },
          {
            "x": 210.63,
            "y": 161.6
          },
          {
            "x": 206.54,
            "y": 169.5
          },
          {
            "x": 203.03,
            "y": 174.18
          },
          {
            "x": 201.28,
            "y": 182.66
          },
          {
            "x": 201.28,
            "y": 182.66
          },
          {
            "x": 201.28,
            "y": 191.43
          },
          {
            "x": 201.28,
            "y": 207.22
          },
          {
            "x": 201.57,
            "y": 211.9
          },
          {
            "x": 198.06,
            "y": 215.7
          },
          {
            "x": 191.92,
            "y": 218.92
          },
          {
            "x": 189.0,
            "y": 222.72
          },
          {
            "x": 198.06,
            "y": 227.4
          },
          {
            "x": 204.49,
            "y": 228.57
          },
          {
            "x": 212.39,
            "y": 231.78
          },
          {
            "x": 213.85,
            "y": 237.34
          },
          {
            "x": 211.8,
            "y": 243.48
          },
          {
            "x": 211.51,
            "y": 244.06
          },
          {
            "x": 210.34,
            "y": 245.82
          },
          {
            "x": 205.96,
            "y": 244.65
          },
          {
            "x": 205.96,
            "y": 244.65
          },
          {
            "x": 205.96,
            "y": 249.03
          },
          {
            "x": 212.1,
            "y": 252.54
          },
          {
            "x": 217.65,
            "y": 257.22
          },
          {
            "x": 224.38,
            "y": 258.98
          },
          {
            "x": 232.27,
            "y": 262.49
          },
          {
            "x": 239.0,
            "y": 267.75
          },
          {
            "x": 243.38,
            "y": 266.87
          },
          {
            "x": 245.72,
            "y": 262.78
          },
          {
            "x": 242.21,
            "y": 258.98
          },
          {
            "x": 235.78,
            "y": 255.47
          },
          {
            "x": 231.4,
            "y": 251.67
          },
          {
            "x": 229.06,
            "y": 247.28
          },
          {
            "x": 228.76,
            "y": 243.77
          },
          {
            "x": 229.64,
            "y": 238.22
          }
        ]
      }
    },
    {
      "name": "African Grey",
      "tag": {}
    }
  ]
}